docs/Makefile
docs/changelog.rst
docs/cli.rst
docs/conf.py
docs/contributing.rst
docs/index.rst
docs/library.rst
docs/requirements.txt
docs/translation.rst
docs/api/api.rst
docs/api/codelist.rst
docs/api/codelist_code.rst
docs/api/exceptions.rst
docs/api/extension.rst
docs/api/extension_registry.rst
docs/api/extension_version.rst
docs/api/profile_builder.rst
docs/api/util.rst
docs/api/versioned_release_schema.rst
ocdsextensionregistry/__init__.py
ocdsextensionregistry/__main__.py
ocdsextensionregistry/api.py
ocdsextensionregistry/codelist.py
ocdsextensionregistry/codelist_code.py
ocdsextensionregistry/exceptions.py
ocdsextensionregistry/extension.py
ocdsextensionregistry/extension_registry.py
ocdsextensionregistry/extension_version.py
ocdsextensionregistry/profile_builder.py
ocdsextensionregistry/util.py
ocdsextensionregistry/versioned_release_schema.py
ocdsextensionregistry/commands/__init__.py
ocdsextensionregistry/commands/base.py
ocdsextensionregistry/commands/download.py
ocdsextensionregistry/commands/generate_data_file.py
ocdsextensionregistry/commands/generate_pot_files.py
ocdsextensionregistry/commands/patched_release_schema.py
ocdsextensionregistry-0.6.9.dist-info/LICENSE
ocdsextensionregistry-0.6.9.dist-info/METADATA
ocdsextensionregistry-0.6.9.dist-info/WHEEL
ocdsextensionregistry-0.6.9.dist-info/entry_points.txt
ocdsextensionregistry-0.6.9.dist-info/top_level.txt
ocdsextensionregistry-0.6.9.dist-info/RECORD
