Metadata-Version: 2.1
Name: ocdsextensionregistry
Version: 0.6.9
Summary: Eases access to information from the extension registry of the Open Contracting Data Standard
Author-email: Open Contracting Partnership <data@open-contracting.org>
License: BSD
Project-URL: Homepage, https://github.com/open-contracting/extension_registry.py
Classifier: License :: OSI Approved :: BSD License
Classifier: Operating System :: OS Independent
Classifier: Programming Language :: Python :: 3.9
Classifier: Programming Language :: Python :: 3.10
Classifier: Programming Language :: Python :: 3.11
Classifier: Programming Language :: Python :: 3.12
Classifier: Programming Language :: Python :: Implementation :: CPython
Classifier: Programming Language :: Python :: Implementation :: PyPy
License-File: LICENSE
Requires-Dist: json-merge-patch
Requires-Dist: jsonref>=1
Requires-Dist: requests
Requires-Dist: requests-cache>=1
Requires-Dist: cattrs!=22.1.0; platform_python_implementation == "PyPy"
Provides-Extra: cli
Requires-Dist: Babel; extra == "cli"
Requires-Dist: MyST-Parser>=0.13.5; extra == "cli"
Requires-Dist: ocds-babel[markdown]>=0.3.3; extra == "cli"
Requires-Dist: Sphinx>=4; extra == "cli"
Provides-Extra: test
Requires-Dist: coverage; extra == "test"
Requires-Dist: pytest; extra == "test"
